argumint/__init__.py
argumint/argu_mint.py
argumint-1.0.5.dist-info/LICENSE
argumint-1.0.5.dist-info/METADATA
argumint-1.0.5.dist-info/WHEEL
argumint-1.0.5.dist-info/top_level.txt
argumint-1.0.5.dist-info/RECORD
