Metadata-Version: 2.1
Name: argumint
Version: 1.0.5
Summary: A fresh new way to handle cli
Author-email: Cariel Becker <cariel.becker@gmx.de>
Maintainer-email: Cariel Becker <cariel.becker@gmx.de>
License: GPL-3.0-or-later
Project-URL: Home, https://pypi.org/project/argumint/
Project-URL: Repository, https://github.com/adalfarus/argumint
Project-URL: Documentation, https://github.com/adalfarus/argumint/wiki
Project-URL: Issue tracker, https://github.com/adalfarus/argumint/issues
Keywords: cli,command line,simplified,fresh
Classifier: Development Status :: 4 - Beta
Classifier: Programming Language :: Python
Classifier: Natural Language :: English
Requires-Python: >=3.9
License-File: LICENSE
Requires-Dist: aplustools
